
<lsccip:addressSpaces xmlns:lsccip="http://www.latticesemi.com/XMLSchema/Radiant/ip">
    <lsccip:addressSpace>
        <lsccip:name>riscv_m_instr_Address_Space</lsccip:name>
        <lsccip:range>0x100000000</lsccip:range>
        <lsccip:width>32</lsccip:width>
    </lsccip:addressSpace>
    <lsccip:addressSpace>
        <lsccip:name>riscv_m_data_Address_Space</lsccip:name>
        <lsccip:range>0x100000000</lsccip:range>
        <lsccip:width>32</lsccip:width>
    </lsccip:addressSpace>
    <lsccip:addressSpace>
        <lsccip:name>CFU_L2_M1_Address_Space</lsccip:name>
        <lsccip:range>0x100000000</lsccip:range>
        <lsccip:width>32</lsccip:width>
    </lsccip:addressSpace>
    <lsccip:addressSpace>
        <lsccip:name>CFU_L2_M0_Address_Space</lsccip:name>
        <lsccip:range>0x100000000</lsccip:range>
        <lsccip:width>32</lsccip:width>
    </lsccip:addressSpace>
    <lsccip:addressSpace>
        <lsccip:name>AXI_M_DATA_Address_Space</lsccip:name>
        <lsccip:range>0x100000000</lsccip:range>
        <lsccip:width>32</lsccip:width>
    </lsccip:addressSpace>
    <lsccip:addressSpace>
        <lsccip:name>AXI_M_INSTR_Address_Space</lsccip:name>
        <lsccip:range>0x100000000</lsccip:range>
        <lsccip:width>32</lsccip:width>
    </lsccip:addressSpace>
    <lsccip:addressSpace>
        <lsccip:name>LOCAL_BUS_M_INSTR_Address_Space</lsccip:name>
        <lsccip:range>0x100000000</lsccip:range>
        <lsccip:width>32</lsccip:width>
    </lsccip:addressSpace>
    <lsccip:addressSpace>
        <lsccip:name>LOCAL_BUS_M_DATA_Address_Space</lsccip:name>
        <lsccip:range>0x100000000</lsccip:range>
        <lsccip:width>32</lsccip:width>
    </lsccip:addressSpace>
    <lsccip:addressSpace>
        <lsccip:name>AXI_REQ_Address_Space</lsccip:name>
        <lsccip:range>0x100000000</lsccip:range>
        <lsccip:width>32</lsccip:width>
    </lsccip:addressSpace>
    <lsccip:addressSpace>
        <lsccip:name>AXI_RESP_Address_Space</lsccip:name>
        <lsccip:range>0x100000000</lsccip:range>
        <lsccip:width>32</lsccip:width>
    </lsccip:addressSpace>
</lsccip:addressSpaces>